destiny_sdk/__init__.py
destiny_sdk/auth.py
destiny_sdk/client.py
destiny_sdk/core.py
destiny_sdk/enhancements.py
destiny_sdk/identifiers.py
destiny_sdk/imports.py
destiny_sdk/py.typed
destiny_sdk/references.py
destiny_sdk/robots.py
destiny_sdk/search.py
destiny_sdk/visibility.py
destiny_sdk/labs/__init__.py
destiny_sdk/labs/references.py
destiny_sdk/parsers/__init__.py
destiny_sdk/parsers/eppi_parser.py
destiny_sdk/parsers/exceptions.py
destiny_sdk-0.8.0.dist-info/METADATA
destiny_sdk-0.8.0.dist-info/WHEEL
destiny_sdk-0.8.0.dist-info/licenses/LICENSE
destiny_sdk-0.8.0.dist-info/RECORD
