Metadata-Version: 2.4
Name: destiny_sdk
Version: 0.8.0
Summary: A software development kit (sdk) to support interaction with the DESTINY repository
Author-email: Adam Hamilton <adam@futureevidence.org>, Andrew Harvey <andrew@futureevidence.org>, Daniel Breves <daniel@futureevidence.org>, Jack Walmisley <jack@futureevidence.org>, Tim Repke <tim.repke@pik-potsdam.de>
License-Expression: Apache-2.0
License-File: LICENSE
Requires-Python: <4,>=3.12
Requires-Dist: cachetools<6,>=5.5.2
Requires-Dist: fastapi<0.116,>=0.115.12
Requires-Dist: httpx<0.29,>=0.28.1
Requires-Dist: msal>=1.34.0
Requires-Dist: pydantic<3,>=2.11.3
Requires-Dist: python-jose<4,>=3.4.0
Provides-Extra: labs
